clsarg/__init__.py
clsarg/clsarg.py
tests/__init__.py
tests/test_argparser.py
clsarg-0.0.6.dist-info/LICENSE
clsarg-0.0.6.dist-info/METADATA
clsarg-0.0.6.dist-info/WHEEL
clsarg-0.0.6.dist-info/top_level.txt
clsarg-0.0.6.dist-info/RECORD
